turn_by_turn/__init__.py
turn_by_turn/ascii.py
turn_by_turn/constants.py
turn_by_turn/doros.py
turn_by_turn/errors.py
turn_by_turn/esrf.py
turn_by_turn/io.py
turn_by_turn/iota.py
turn_by_turn/lhc.py
turn_by_turn/madng.py
turn_by_turn/ptc.py
turn_by_turn/sps.py
turn_by_turn/structures.py
turn_by_turn/trackone.py
turn_by_turn/utils.py
turn_by_turn/xtrack_line.py
turn_by_turn-0.9.1.dist-info/METADATA
turn_by_turn-0.9.1.dist-info/WHEEL
turn_by_turn-0.9.1.dist-info/licenses/LICENSE
turn_by_turn-0.9.1.dist-info/RECORD
