Metadata-Version: 2.4
Name: turn_by_turn
Version: 0.9.1
Summary: Read and write turn-by-turn measurement files from different particle accelerator formats.
Project-URL: homepage, https://github.com/pylhc/turn_by_turn
Project-URL: repository, https://github.com/pylhc/turn_by_turn
Project-URL: documentation, https://pylhc.github.io/turn_by_turn/
Author-email: OMC Team <pylhc@github.com>
License-Expression: MIT
License-File: LICENSE
Classifier: Development Status :: 5 - Production/Stable
Classifier: Intended Audience :: Science/Research
Classifier: Natural Language :: English
Classifier: Operating System :: OS Independent
Classifier: Programming Language :: Python :: 3 :: Only
Classifier: Programming Language :: Python :: 3.10
Classifier: Programming Language :: Python :: 3.11
Classifier: Programming Language :: Python :: 3.12
Classifier: Programming Language :: Python :: Implementation :: CPython
Classifier: Topic :: Scientific/Engineering
Classifier: Topic :: Software Development :: Libraries :: Python Modules
Classifier: Typing :: Typed
Requires-Python: >=3.10
Requires-Dist: h5py>=2.9
Requires-Dist: numpy>=1.24
Requires-Dist: pandas>=2.1
Requires-Dist: scipy>=1.5
Requires-Dist: sdds>=0.4
Provides-Extra: all
Requires-Dist: pytest-cov>=2.9; extra == 'all'
Requires-Dist: pytest>=7.0; extra == 'all'
Requires-Dist: setuptools>=65; extra == 'all'
Requires-Dist: sphinx-rtd-theme>=2.0; extra == 'all'
Requires-Dist: sphinx>=7.0; extra == 'all'
Requires-Dist: tfs-pandas>=4.0.0; extra == 'all'
Requires-Dist: xpart>=0.23.0; extra == 'all'
Requires-Dist: xtrack>=0.84.7; extra == 'all'
Provides-Extra: doc
Requires-Dist: sphinx-rtd-theme>=2.0; extra == 'doc'
Requires-Dist: sphinx>=7.0; extra == 'doc'
Provides-Extra: madng
Requires-Dist: tfs-pandas>=4.0.0; extra == 'madng'
Provides-Extra: test
Requires-Dist: pytest-cov>=2.9; extra == 'test'
Requires-Dist: pytest>=7.0; extra == 'test'
Requires-Dist: setuptools>=65; extra == 'test'
Requires-Dist: tfs-pandas>=4.0.0; extra == 'test'
Requires-Dist: xpart>=0.23.0; extra == 'test'
Requires-Dist: xtrack>=0.84.7; extra == 'test'
Provides-Extra: xtrack
Requires-Dist: setuptools>=65; extra == 'xtrack'
Requires-Dist: xpart>=0.23.0; extra == 'xtrack'
Requires-Dist: xtrack>=0.84.7; extra == 'xtrack'
